README.rst
setup.py
cmdssh/__init__.py
cmdssh/scp.py
cmdssh.egg-info/PKG-INFO
cmdssh.egg-info/SOURCES.txt
cmdssh.egg-info/dependency_links.txt
cmdssh.egg-info/requires.txt
cmdssh.egg-info/top_level.txt
cmdssh.egg-info/zip-safe